__init__.py
__main__.py
snakebuild-0.0.1.dist-info/METADATA
snakebuild-0.0.1.dist-info/WHEEL
snakebuild-0.0.1.dist-info/top_level.txt
snakebuild-0.0.1.dist-info/RECORD
