Metadata-Version: 2.1
Name: snakebuild
Version: 0.0.1
Summary: Originally named Pybuild. It is a new build system written in Python, because y not?
Author-email: Khyle Isaias <khyleisaias@gmail.com>
Project-URL: Homepage, https://github.com/khyleisaias/pybuild
Project-URL: Bug Tracker, https://github.com/khyleisaias/pybuild/issues
Classifier: Programming Language :: Python :: 3
Classifier: License :: OSI Approved :: MIT License
Classifier: Operating System :: OS Independent
Requires-Python: >=3.6
